{
  "words": [
    {"ko":"권력","lv":6,"cat":"政治经济","zh_hint":"权力"},
    {"ko":"민주주의","lv":6,"cat":"政治经济","zh_hint":"民主主义"},
    {"ko":"의회","lv":6,"cat":"政治经济","zh_hint":"议会"},
    {"ko":"개헌","lv":6,"cat":"政治经济","zh_hint":"修宪"},
    {"ko":"헌법","lv":6,"cat":"政治经济","zh_hint":"宪法"},
    {"ko":"사법","lv":6,"cat":"政治经济","zh_hint":"司法"},
    {"ko":"입법","lv":6,"cat":"政治经济","zh_hint":"立法"},
    {"ko":"행정","lv":6,"cat":"政治经济","zh_hint":"行政"},
    {"ko":"부패","lv":6,"cat":"政治经济","zh_hint":"腐败"},
    {"ko":"개혁","lv":6,"cat":"政治经济","zh_hint":"改革"},
    {"ko":"국고","lv":6,"cat":"政治经济","zh_hint":"国库"},
    {"ko":"재정적자","lv":6,"cat":"政治经济","zh_hint":"财政赤字"},
    {"ko":"물가상승","lv":6,"cat":"政治经济","zh_hint":"物价上涨"},
    {"ko":"경기침체","lv":6,"cat":"政治经济","zh_hint":"经济衰退"},
    {"ko":"인프라","lv":6,"cat":"政治经济","zh_hint":"基础设施"},
    {"ko":"부채","lv":6,"cat":"政治经济","zh_hint":"负债"},
    {"ko":"주식","lv":6,"cat":"政治经济","zh_hint":"股票"},
    {"ko":"부동산","lv":6,"cat":"政治经济","zh_hint":"房地产"},
    {"ko":"양적완화","lv":6,"cat":"政治经济","zh_hint":"量化宽松"},
    {"ko":"독점","lv":6,"cat":"政治经济","zh_hint":"垄断"},
    {"ko":"공정거래","lv":6,"cat":"政治经济","zh_hint":"公平交易"},
    {"ko":"국제통화","lv":6,"cat":"政治经济","zh_hint":"国际货币"},
    {"ko":"경상수지","lv":6,"cat":"政治经济","zh_hint":"经常收支"},
    {"ko":"지속가능성","lv":6,"cat":"政治经济","zh_hint":"可持续性"},
    {"ko":"소득불평등","lv":6,"cat":"政治经济","zh_hint":"收入不平等"},
    {"ko":"반독점","lv":6,"cat":"政治经济","zh_hint":"反垄断"},
    {"ko":"보호무역","lv":6,"cat":"政治经济","zh_hint":"保护贸易"},
    {"ko":"긴축","lv":6,"cat":"政治经济","zh_hint":"紧缩"},
    {"ko":"신자유주의","lv":6,"cat":"政治经济","zh_hint":"新自由主义"},
    {"ko":"세계화","lv":6,"cat":"政治经济","zh_hint":"全球化"},
    {"ko":"이주","lv":6,"cat":"社会文化","zh_hint":"移居"},
    {"ko":"난민","lv":6,"cat":"社会文化","zh_hint":"难民"},
    {"ko":"포용","lv":6,"cat":"社会文化","zh_hint":"包容"},
    {"ko":"공동체","lv":6,"cat":"社会文化","zh_hint":"共同体"},
    {"ko":"계층","lv":6,"cat":"社会文化","zh_hint":"阶层"},
    {"ko":"빈곤","lv":6,"cat":"社会文化","zh_hint":"贫困"},
    {"ko":"불평등","lv":6,"cat":"社会文化","zh_hint":"不平等"},
    {"ko":"사회안전망","lv":6,"cat":"社会文化","zh_hint":"社会安全网"},
    {"ko":"고립","lv":6,"cat":"社会文化","zh_hint":"孤立"},
    {"ko":"세대갈등","lv":6,"cat":"社会文化","zh_hint":"代际矛盾"},
    {"ko":"지역격차","lv":6,"cat":"社会文化","zh_hint":"地区差距"},
    {"ko":"인종차별","lv":6,"cat":"社会文化","zh_hint":"种族歧视"},
    {"ko":"성차별","lv":6,"cat":"社会文化","zh_hint":"性别歧视"},
    {"ko":"매스컴","lv":6,"cat":"社会文化","zh_hint":"大众传媒"},
    {"ko":"SNS","lv":6,"cat":"社会文化","zh_hint":"社交媒体"},
    {"ko":"정보화","lv":6,"cat":"社会文化","zh_hint":"信息化"},
    {"ko":"도시화","lv":6,"cat":"社会文化","zh_hint":"城市化"},
    {"ko":"핵가족","lv":6,"cat":"社会文化","zh_hint":"核心家庭"},
    {"ko":"1인가구","lv":6,"cat":"社会文化","zh_hint":"单人家庭"},
    {"ko":"저출생","lv":6,"cat":"社会文化","zh_hint":"低生育"},
    {"ko":"초고령사회","lv":6,"cat":"社会文化","zh_hint":"超老龄社会"},
    {"ko":"복지국가","lv":6,"cat":"社会文化","zh_hint":"福利国家"},
    {"ko":"시민사회","lv":6,"cat":"社会文化","zh_hint":"市民社会"},
    {"ko":"비정부기구","lv":6,"cat":"社会文化","zh_hint":"非政府组织"},
    {"ko":"이데올로기","lv":6,"cat":"社会文化","zh_hint":"意识形态"},
    {"ko":"양자","lv":6,"cat":"科学技术","zh_hint":"量子"},
    {"ko":"바이오","lv":6,"cat":"科学技术","zh_hint":"生物"},
    {"ko":"자율주행","lv":6,"cat":"科学技术","zh_hint":"自动驾驶"},
    {"ko":"암호화","lv":6,"cat":"科学技术","zh_hint":"加密"},
    {"ko":"사물인터넷","lv":6,"cat":"科学技术","zh_hint":"物联网"},
    {"ko":"클라우드","lv":6,"cat":"科学技术","zh_hint":"云"},
    {"ko":"블록체인","lv":6,"cat":"科学技术","zh_hint":"区块链"},
    {"ko":"메타버스","lv":6,"cat":"科学技术","zh_hint":"元宇宙"},
    {"ko":"유전자","lv":6,"cat":"科学技术","zh_hint":"基因"},
    {"ko":"복제","lv":6,"cat":"科学技术","zh_hint":"克隆"},
    {"ko":"우주탐사","lv":6,"cat":"科学技术","zh_hint":"宇宙探索"},
    {"ko":"신재생에너지","lv":6,"cat":"科学技术","zh_hint":"新能源"},
    {"ko":"핵융합","lv":6,"cat":"科学技术","zh_hint":"核聚变"},
    {"ko":"반도체","lv":6,"cat":"科学技术","zh_hint":"半导体"},
    {"ko":"알고리즘","lv":6,"cat":"科学技术","zh_hint":"算法"},
    {"ko":"사이버","lv":6,"cat":"科学技术","zh_hint":"网络"},
    {"ko":"기술격차","lv":6,"cat":"科学技术","zh_hint":"技术差距"},
    {"ko":"연구개발","lv":6,"cat":"科学技术","zh_hint":"研发"},
    {"ko":"지식재산권","lv":6,"cat":"科学技术","zh_hint":"知识产权"},
    {"ko":"탄소중립","lv":6,"cat":"环境健康","zh_hint":"碳中和"},
    {"ko":"생물다양성","lv":6,"cat":"环境健康","zh_hint":"生物多样性"},
    {"ko":"환경영향평가","lv":6,"cat":"环境健康","zh_hint":"环境影响评估"},
    {"ko":"대기오염","lv":6,"cat":"环境健康","zh_hint":"大气污染"},
    {"ko":"수질오염","lv":6,"cat":"环境健康","zh_hint":"水质污染"},
    {"ko":"토양오염","lv":6,"cat":"环境健康","zh_hint":"土壤污染"},
    {"ko":"미세먼지","lv":6,"cat":"环境健康","zh_hint":"细颗粒物"},
    {"ko":"기후위기","lv":6,"cat":"环境健康","zh_hint":"气候危机"},
    {"ko":"온실가스","lv":6,"cat":"环境健康","zh_hint":"温室气体"},
    {"ko":"해수면상승","lv":6,"cat":"环境健康","zh_hint":"海平面上升"},
    {"ko":"사막화","lv":6,"cat":"环境健康","zh_hint":"荒漠化"},
    {"ko":"환경규제","lv":6,"cat":"环境健康","zh_hint":"环境规制"},
    {"ko":"순환경제","lv":6,"cat":"环境健康","zh_hint":"循环经济"},
    {"ko":"친환경","lv":6,"cat":"环境健康","zh_hint":"环保"},
    {"ko":"감염병","lv":6,"cat":"环境健康","zh_hint":"传染病"},
    {"ko":"팬데믹","lv":6,"cat":"环境健康","zh_hint":"大流行"},
    {"ko":"백신","lv":6,"cat":"环境健康","zh_hint":"疫苗"},
    {"ko":"만성질환","lv":6,"cat":"环境健康","zh_hint":"慢性病"},
    {"ko":"정신건강","lv":6,"cat":"环境健康","zh_hint":"精神健康"},
    {"ko":"공중보건","lv":6,"cat":"环境健康","zh_hint":"公共卫生"},
    {"ko":"원격의료","lv":6,"cat":"环境健康","zh_hint":"远程医疗"},
    {"ko":"수명","lv":6,"cat":"环境健康","zh_hint":"寿命"},
    {"ko":"고령사회","lv":6,"cat":"环境健康","zh_hint":"老龄社会"},
    {"ko":"모순","lv":6,"cat":"抽象学术","zh_hint":"矛盾"},
    {"ko":"본질","lv":6,"cat":"抽象学术","zh_hint":"本质"},
    {"ko":"인과","lv":6,"cat":"抽象学术","zh_hint":"因果"},
    {"ko":"패러다임","lv":6,"cat":"抽象学术","zh_hint":"范式"},
    {"ko":"딜레마","lv":6,"cat":"抽象学术","zh_hint":"两难"},
    {"ko":"통찰","lv":6,"cat":"抽象学术","zh_hint":"洞察"},
    {"ko":"맹점","lv":6,"cat":"抽象学术","zh_hint":"盲点"},
    {"ko":"함의","lv":6,"cat":"抽象学术","zh_hint":"含义"},
    {"ko":"정당성","lv":6,"cat":"抽象学术","zh_hint":"正当性"},
    {"ko":"당위성","lv":6,"cat":"抽象学术","zh_hint":"应然性"},
    {"ko":"수반하다","lv":6,"cat":"抽象学术","zh_hint":"伴随"},
    {"ko":"야기하다","lv":6,"cat":"抽象学术","zh_hint":"引起"},
    {"ko":"절감하다","lv":6,"cat":"抽象学术","zh_hint":"切实感受"},
    {"ko":"간과하다","lv":6,"cat":"抽象学术","zh_hint":"忽视"},
    {"ko":"배제하다","lv":6,"cat":"抽象学术","zh_hint":"排除"},
    {"ko":"간주하다","lv":6,"cat":"抽象学术","zh_hint":"视为"},
    {"ko":"유발하다","lv":6,"cat":"抽象学术","zh_hint":"诱发"},
    {"ko":"초래하다","lv":6,"cat":"抽象学术","zh_hint":"招致"},
    {"ko":"제고하다","lv":6,"cat":"抽象学术","zh_hint":"提高"},
    {"ko":"촉진하다","lv":6,"cat":"抽象学术","zh_hint":"促进"},
    {"ko":"저해하다","lv":6,"cat":"抽象学术","zh_hint":"阻碍"},
    {"ko":"상충하다","lv":6,"cat":"抽象学术","zh_hint":"冲突"},
    {"ko":"파생하다","lv":6,"cat":"抽象学术","zh_hint":"派生"},
    {"ko":"공존하다","lv":6,"cat":"抽象学术","zh_hint":"共存"},
    {"ko":"모색하다","lv":6,"cat":"抽象学术","zh_hint":"摸索"},
    {"ko":"집약하다","lv":6,"cat":"抽象学术","zh_hint":"集约"},
    {"ko":"도출하다","lv":6,"cat":"抽象学术","zh_hint":"导出"},
    {"ko":"규명하다","lv":6,"cat":"抽象学术","zh_hint":"查明"},
    {"ko":"전제하다","lv":6,"cat":"抽象学术","zh_hint":"前提"},
    {"ko":"가정하다","lv":6,"cat":"抽象学术","zh_hint":"假定"},
    {"ko":"추론하다","lv":6,"cat":"抽象学术","zh_hint":"推论"},
    {"ko":"도래하다","lv":6,"cat":"抽象学术","zh_hint":"到来"},
    {"ko":"만연하다","lv":6,"cat":"抽象学术","zh_hint":"蔓延"},
    {"ko":"표출하다","lv":6,"cat":"抽象学术","zh_hint":"表露"},
    {"ko":"내포하다","lv":6,"cat":"抽象学术","zh_hint":"内涵"},
    {"ko":"수렴하다","lv":6,"cat":"抽象学术","zh_hint":"收敛"},
    {"ko":"분출하다","lv":6,"cat":"抽象学术","zh_hint":"喷发"},
    {"ko":"잠식하다","lv":6,"cat":"抽象学术","zh_hint":"侵蚀"},
    {"ko":"와해되다","lv":6,"cat":"抽象学术","zh_hint":"瓦解"},
    {"ko":"뿌리 깊다","lv":6,"cat":"惯用语俗语","zh_hint":"根深蒂固"},
    {"ko":"산 넘어 산","lv":6,"cat":"惯用语俗语","zh_hint":"一波未平一波又起"},
    {"ko":"발 벗고 나서다","lv":6,"cat":"惯用语俗语","zh_hint":"挺身而出"},
    {"ko":"진땀을 빼다","lv":6,"cat":"惯用语俗语","zh_hint":"费九牛二虎之力"},
    {"ko":"비행기를 태우다","lv":6,"cat":"惯用语俗语","zh_hint":"捧上天"},
    {"ko":"손에 땀을 쥐다","lv":6,"cat":"惯用语俗语","zh_hint":"捏一把汗"},
    {"ko":"간이 크다","lv":6,"cat":"惯用语俗语","zh_hint":"胆子大"},
    {"ko":"눈이 높다","lv":6,"cat":"惯用语俗语","zh_hint":"眼光高"},
    {"ko":"입이 가볍다","lv":6,"cat":"惯用语俗语","zh_hint":"嘴不严"},
    {"ko":"코가 납작하다","lv":6,"cat":"惯用语俗语","zh_hint":"碰一鼻子灰"},
    {"ko":"허리가 휘다","lv":6,"cat":"惯用语俗语","zh_hint":"不堪重负"},
    {"ko":"발등에 불 떨어지다","lv":6,"cat":"惯用语俗语","zh_hint":"火烧眉毛"},
    {"ko":"내지","lv":6,"cat":"连接表达","zh_hint":"或"},
    {"ko":"고사하고","lv":6,"cat":"连接表达","zh_hint":"别说"},
    {"ko":"더더욱","lv":6,"cat":"连接表达","zh_hint":"更加"},
    {"ko":"도저히","lv":6,"cat":"连接表达","zh_hint":"怎么也"},
    {"ko":"기껏해야","lv":6,"cat":"连接表达","zh_hint":"顶多"},
    {"ko":"간혹","lv":6,"cat":"连接表达","zh_hint":"偶尔"},
    {"ko":"불과하다","lv":6,"cat":"连接表达","zh_hint":"不过"},
    {"ko":"기실","lv":6,"cat":"连接表达","zh_hint":"其实"},
    {"ko":"더군다나","lv":6,"cat":"连接表达","zh_hint":"更不用说"},
    {"ko":"부디","lv":6,"cat":"连接表达","zh_hint":"请务必"}
  ]
}
